[
  {
    "name": "Arid Coast",
    "img": "/data/board/arid_coast.png"
  },
  {
    "name": "Badlands Necrotite Mine",
    "img": "/data/board/badlands_necrotite_mine.png"
  },
  {
    "name": "Crag Outskirts",
    "img": "/data/board/crag_outskirts.png"
  },
  {
    "name": "Dustbowl",
    "img": "/data/board/dustbowl.png"
  },
  {
    "name": "Fire and Ice",
    "img": "/data/board/fire_and_ice.png"
  },
  {
    "name": "Lumberyard",
    "img": "/data/board/lumberyard.png"
  },
  {
    "name": "Mud Village",
    "img": "/data/board/mud_village.png"
  },
  {
    "name": "Orgoth Excavation",
    "img": "/data/board/orgoth_excavation.png"
  },
  {
    "name": "Snow Drift",
    "img": "/data/board/snow_drift.png"
  },
  {
    "name": "Vive la resistance",
    "img": "/data/board/vive_la_resistance.png",
    "terrain": {
      "rect": [
        {
          "type": "obstruction",
          "x": 150,
          "y": 157,
          "width": 60,
          "height": 44,
          "rotate": 40
        },
        {
          "type": "obstruction",
          "x": 338,
          "y": 340,
          "width": 85,
          "height": 64,
          "rotate": 40
        },
        {
          "type": "linear",
          "x": 240,
          "y": 245,
          "width": 70,
          "height": 7,
          "rotate": 84
        }
      ],
      "circle": [
        {
          "type": "forest",
          "x": 90,
          "y": 242,
          "r": 29
        },
        {
          "type": "forest",
          "x": 390,
          "y": 242,
          "r": 29
        }
      ]
    }
  }
]
